dm2022exp/__init__.py
dm2022exp_hzau-1.0.1.dist-info/METADATA
dm2022exp_hzau-1.0.1.dist-info/WHEEL
dm2022exp_hzau-1.0.1.dist-info/top_level.txt
dm2022exp_hzau-1.0.1.dist-info/RECORD
