Metadata-Version: 2.1
Name: dm2022exp-hzau
Version: 1.0.1
Summary: experimental package of HZAU 2022 data mining course
Author: HuChang
Author-email: changlehung@gmail.com
